fpcli/__init__.py
fpcli/fpcli_settings.py
fpcli/choice/__init__.py
fpcli/choice/startproject.py
fpcli/commands/__init__.py
fpcli/commands/basic.py
fpcli/commands/collect_static.py
fpcli/commands/dbseed.py
fpcli/commands/dbshell.py
fpcli/commands/dumpdata.py
fpcli/commands/loaddata.py
fpcli/commands/make.py
fpcli/commands/migrations.py
fpcli/commands/pyshell.py
fpcli/commands/startapp.py
fpcli/commands/startproject.py
fpcli/commands/testmail.py
fpcli/commands/unittest.py
fpcli/connection/__init__.py
fpcli/connection/postgresql.py
fpcli/function/__init__.py
fpcli/function/basic.py
fpcli/function/check_app.py
fpcli/function/check_class.py
fpcli/function/get_settings.py
fpcli/function/make_ai_test_case.py
fpcli/function/makeapp.py
fpcli/function/startproject.py
fpcli/template/__init__.py
fpcli/template/cli_content.py
fpcli/template/startapp.py
fpcli/template/startproject.py
fpcli-0.1.41.dist-info/METADATA
fpcli-0.1.41.dist-info/WHEEL
fpcli-0.1.41.dist-info/entry_points.txt
fpcli-0.1.41.dist-info/top_level.txt
fpcli-0.1.41.dist-info/RECORD
