Metadata-Version: 2.2
Name: fpcli
Version: 0.1.41
Summary: This the simple command line interface using this package  you can easly integrate the command line interface for fastapi which is developed into the typer package 
Author: Rohit kumar
Classifier: Programming Language :: Python :: 3
Classifier: License :: OSI Approved :: MIT License
Classifier: Operating System :: OS Independent
Requires-Dist: typer
Dynamic: author
Dynamic: classifier
Dynamic: requires-dist
Dynamic: summary
